regrex/SingleLineFunction.py
regrex/__init__.py
regrex/dataset.py
regrex/linear_model.py
regrex/log.py
regrex/polynomial_model.py
regrex/preprocess.py
regrex/statistics.py
regrex/transform.py
regrex/validation.py
regrex-0.6.dist-info/METADATA
regrex-0.6.dist-info/WHEEL
regrex-0.6.dist-info/top_level.txt
regrex-0.6.dist-info/RECORD
