Metadata-Version: 2.1
Name: regrex
Version: 0.6
Summary: regression made easy with regrex !
Home-page: https://github.com/rushan7750/regress
Author: rushan7750
Author-email: shanrsjmax@gmail.com
License: MIT
Download-URL: https://github.com/rushan7750/regress/archive/0.6.tar.gz
Keywords: regress,simple,regrex
Platform: UNKNOWN
Classifier: Development Status :: 3 - Alpha
Classifier: Intended Audience :: Developers
Classifier: Topic :: Software Development :: Build Tools
Classifier: License :: OSI Approved :: MIT License
Classifier: Programming Language :: Python :: 3
Classifier: Programming Language :: Python :: 3.4
Classifier: Programming Language :: Python :: 3.5
Classifier: Programming Language :: Python :: 3.6
Requires-Dist: scikit-learn
